{
    "CreatedDate": "2021-03-31T08:34:56.097",
    "CustomerKey": "82713BEE-5344-4F79-BD39-64F4E3E26B07",
    "Name": "UNSUBS_OUTSIDE_CLOUD_PAGE_HISTORY_DE",
    "Description": "",
    "IsSendable": "false",
    "IsTestable": "false",
    "RowBasedRetention": "false",
    "ResetRetentionPeriodOnImport": "false",
    "DeleteAtEndOfRetentionPeriod": "false",
    "RetainUntil": "",
    "Fields": [
        {
            "Name": "ContactKey",
            "Scale": "0",
            "DefaultValue": "",
            "MaxLength": "18",
            "IsRequired": "true",
            "IsPrimaryKey": "true",
            "FieldType": "Text"
        },
        {
            "Name": "Email",
            "Scale": "0",
            "DefaultValue": "",
            "MaxLength": "254",
            "IsRequired": "true",
            "IsPrimaryKey": "true",
            "FieldType": "EmailAddress"
        },
        {
            "Name": "Date Of Unsubscription",
            "Scale": "0",
            "DefaultValue": "",
            "IsRequired": "true",
            "IsPrimaryKey": "true",
            "FieldType": "Date"
        },
        {
            "Name": "Reason Of Unsubscription",
            "DefaultValue": "",
            "MaxLength": "500",
            "IsRequired": "true",
            "IsPrimaryKey": "false",
            "FieldType": "Text"
        }
    ],
    "r__folder_ContentType": "dataextension",
    "r__folder_Path": "Data Extensions/UNSUBSCRIBES/UNSUBS OUTSIDE LANDING PAGE"
}
