{
    "CreatedDate": "2021-04-22T04:12:20.993",
    "CustomerKey": "962CF5CD-A13D-4688-8D39-E9959C4171DF",
    "Name": "STORE MANAGERS",
    "Description": "",
    "IsSendable": "false",
    "IsTestable": "false",
    "RowBasedRetention": "false",
    "ResetRetentionPeriodOnImport": "false",
    "DeleteAtEndOfRetentionPeriod": "false",
    "RetainUntil": "",
    "Fields": [
        {
            "Name": "Full Name",
            "Scale": "0",
            "DefaultValue": "",
            "MaxLength": "255",
            "IsRequired": "true",
            "IsPrimaryKey": "true",
            "FieldType": "Text"
        },
        {
            "Name": "Title",
            "Scale": "0",
            "DefaultValue": "",
            "MaxLength": "50",
            "IsRequired": "true",
            "IsPrimaryKey": "true",
            "FieldType": "Text"
        },
        {
            "Name": "MC SAP Email Address",
            "Scale": "0",
            "DefaultValue": "",
            "MaxLength": "254",
            "IsRequired": "true",
            "IsPrimaryKey": "false",
            "FieldType": "EmailAddress"
        },
        {
            "Name": "Country",
            "Scale": "0",
            "DefaultValue": "",
            "MaxLength": "50",
            "IsRequired": "true",
            "IsPrimaryKey": "false",
            "FieldType": "Text"
        },
        {
            "Name": "Phone",
            "Scale": "0",
            "DefaultValue": "",
            "MaxLength": "50",
            "IsRequired": "true",
            "IsPrimaryKey": "false",
            "FieldType": "Phone"
        },
        {
            "Name": "City",
            "Scale": "0",
            "DefaultValue": "",
            "MaxLength": "255",
            "IsRequired": "true",
            "IsPrimaryKey": "false",
            "FieldType": "Text"
        },
        {
            "Name": "Addresse Line 1",
            "Scale": "0",
            "DefaultValue": "",
            "MaxLength": "1500",
            "IsRequired": "true",
            "IsPrimaryKey": "false",
            "FieldType": "Text"
        },
        {
            "Name": "Addresse Line 2",
            "Scale": "0",
            "DefaultValue": "",
            "MaxLength": "1500",
            "IsRequired": "false",
            "IsPrimaryKey": "false",
            "FieldType": "Text"
        },
        {
            "Name": "Addresse Line 3",
            "Scale": "0",
            "DefaultValue": "",
            "MaxLength": "1500",
            "IsRequired": "true",
            "IsPrimaryKey": "false",
            "FieldType": "Text"
        }
    ],
    "r__folder_ContentType": "dataextension",
    "r__folder_Path": "Data Extensions/TestDE"
}
